exasol/secret_store.py
notebook_connector-0.0.1.dist-info/entry_points.txt
notebook_connector-0.0.1.dist-info/LICENSE
notebook_connector-0.0.1.dist-info/WHEEL
notebook_connector-0.0.1.dist-info/METADATA
notebook_connector-0.0.1.dist-info/RECORD
